[
  {
    "language": "en",
    "info": [
      {
        "title": "62",
        "description": "Years"
      },
      {
        "title": "4",
        "description": "Affiliates"
      },
      {
        "title": "3",
        "description": "Industries"
      },
      {
        "title": "1.4B",
        "description": "Wealth"
      }
    ],
    "images": [
      {
        "url": "../../images/business-overview-square1.png"
      },
      {
        "url": "../../images/business-overview-square2.png"
      },
      {
        "url": "../../images/business-overview-square3.png"
      },
      {
        "url": "../../images/business-overview-square4.png"
      }
    ]
  },
  {
    "language": "th",
    "info": [
      {
        "title": "62",
        "description": "Years"
      },
      {
        "title": "4",
        "description": "Affiliates"
      },
      {
        "title": "3",
        "description": "Industries"
      },
      {
        "title": "1.4B",
        "description": "Wealth"
      }
    ],
    "images": [
      {
        "url": "../../images/business-overview-square1.png"
      },
      {
        "url": "../../images/business-overview-square2.png"
      },
      {
        "url": "../../images/business-overview-square3.png"
      },
      {
        "url": "../../images/business-overview-square4.png"
      }
    ]
  }
]
